pdf2up/__init__.py
pdf2up/__main__.py
pdf2up/batch_multiprocessing.py
pdf2up/cli.py
pdf2up/console_log.py
pdf2up/conversion.py
pdf2up-0.2.4.dist-info/LICENSE
pdf2up-0.2.4.dist-info/METADATA
pdf2up-0.2.4.dist-info/WHEEL
pdf2up-0.2.4.dist-info/entry_points.txt
pdf2up-0.2.4.dist-info/top_level.txt
pdf2up-0.2.4.dist-info/RECORD
