Metadata-Version: 2.1
Name: pdf2up
Version: 0.2.4
Summary: A small utility to generate fairly high resolution preview images of PDFs suitable for viewing or sharing to social media
Home-page: https://github.com/lmmx/pdf2up
Author: Louis Maddox
Author-email: louismmx@gmail.com
License: MIT License
Platform: UNKNOWN
Classifier: Programming Language :: Python :: 3
Classifier: Operating System :: OS Independent
Classifier: License :: OSI Approved :: MIT License
Classifier: Intended Audience :: Developers
Requires-Python: >=3
License-File: LICENSE
Requires-Dist: imageio
Requires-Dist: pdfCropMargins
Requires-Dist: pdf2image
Requires-Dist: PyPDF2
Requires-Dist: more-itertools
Requires-Dist: tqdm
Requires-Dist: argcomplete
